mondir/__init__.py
mondir/api.py
mondir/jinja2/__init__.py
mondir/jinja2/extension.py
mondir/jinja2/loaders.py
mondir/jinja2/utils.py
mondir/utils/pseudo_list.py
mondir-0.1.0.dist-info/METADATA
mondir-0.1.0.dist-info/WHEEL
mondir-0.1.0.dist-info/RECORD
