Metadata-Version: 2.1
Name: mondir
Version: 0.1.0
Summary: Directory/filesystem-level templating using Jinja2
Author: smheidrich
Author-email: smheidrich@weltenfunktion.de
Requires-Python: >=3.12,<4.0
Classifier: Programming Language :: Python :: 3
Requires-Dist: jaraco-classes (>=3.2.3,<4.0.0)
Requires-Dist: jinja2 (>=3.1.2,<4.0.0)
